coltrane/__init__.py
coltrane/console.py
coltrane/context_processors.py
coltrane/exceptions.py
coltrane/feeds.py
coltrane/finders.py
coltrane/manifest.py
coltrane/middleware.py
coltrane/module_finder.py
coltrane/renderer.py
coltrane/retriever.py
coltrane/sitemaps.py
coltrane/urls.py
coltrane/utils.py
coltrane/views.py
coltrane/wildcard_templates.py
coltrane/config/__init__.py
coltrane/config/cache.py
coltrane/config/paths.py
coltrane/config/redirects.py
coltrane/config/settings.py
coltrane/config/coltrane/__init__.py
coltrane/config/coltrane/configurators/__init__.py
coltrane/config/coltrane/configurators/templates.py
coltrane/default-files/Dockerfile
coltrane/default-files/README.md
coltrane/default-files/app.py
coltrane/default-files/coltrane.toml
coltrane/default-files/env
coltrane/default-files/gitignore
coltrane/default-files/gunicorn.conf.py
coltrane/default-files/pyproject.toml
coltrane/default-files/watchmanconfig
coltrane/management/__init__.py
coltrane/management/commands/__init__.py
coltrane/management/commands/build.py
coltrane/templates/coltrane/base.html
coltrane/templates/coltrane/content.html
coltrane/templatetags/__init__.py
coltrane/templatetags/coltrane_tags.py
coltrane-0.39.0.dist-info/METADATA
coltrane-0.39.0.dist-info/WHEEL
coltrane-0.39.0.dist-info/entry_points.txt
coltrane-0.39.0.dist-info/licenses/LICENSE
coltrane-0.39.0.dist-info/RECORD
