Metadata-Version: 2.4
Name: coltrane
Version: 0.39.0
Summary: A minimal app framework for content sites 🎵
Project-URL: Homepage, https://github.com/adamghill/coltrane
Project-URL: Documentation, https://github.com/adamghill/coltrane
Project-URL: Repository, https://github.com/adamghill/coltrane.git
Project-URL: Issues, https://github.com/adamghill/coltrane/discussions
Project-URL: Changelog, https://github.com/adamghill/coltrane/blob/master/CHANGELOG.md
Author-email: Adam Hill <adam@adamghill.com>
License: MIT License
License-File: LICENSE
Keywords: django,markdown,python,static
Classifier: Development Status :: 3 - Alpha
Classifier: Intended Audience :: Developers
Classifier: License :: OSI Approved :: MIT License
Classifier: Programming Language :: Python :: 3.10
Classifier: Programming Language :: Python :: 3.11
Classifier: Programming Language :: Python :: 3.12
Requires-Python: <4.0,>=3.10
Requires-Dist: click-aliases<2
Requires-Dist: click>=8
Requires-Dist: dateparser>=1
Requires-Dist: django-browser-reload<2
Requires-Dist: django-fastdev<2
Requires-Dist: django>=3.0
Requires-Dist: halo<1
Requires-Dist: minestrone>=0.6.2
Requires-Dist: mistune>=3
Requires-Dist: msgspec<1
Requires-Dist: pygments>=2.7.3
Requires-Dist: python-dotenv>0.17
Requires-Dist: python-frontmatter>=1
Requires-Dist: pywatchman>1
Requires-Dist: rich-click<2
Provides-Extra: angles
Requires-Dist: dj-angles>0; extra == 'angles'
Provides-Extra: compressor
Requires-Dist: django-compressor<5; extra == 'compressor'
Provides-Extra: deploy
Requires-Dist: gunicorn>21; extra == 'deploy'
Requires-Dist: whitenoise>6; extra == 'deploy'
Provides-Extra: docs
Requires-Dist: attrs>0; extra == 'docs'
Requires-Dist: furo>0; extra == 'docs'
Requires-Dist: linkify-it-py>0; extra == 'docs'
Requires-Dist: myst-parser>0; extra == 'docs'
Requires-Dist: sphinx-autobuild>0; extra == 'docs'
Requires-Dist: sphinx-copybutton>0; extra == 'docs'
Requires-Dist: sphinx-inline-tabs>0; extra == 'docs'
Requires-Dist: sphinx>7; extra == 'docs'
Requires-Dist: toml>0; extra == 'docs'
Provides-Extra: json5
Requires-Dist: pyjson5>0; extra == 'json5'
Provides-Extra: unicorn
Requires-Dist: django-unicorn>0; extra == 'unicorn'
